PuppeteerPercy/__init__.py
robotframework_puppeteer_percy-0.1.1.dist-info/LICENSE
robotframework_puppeteer_percy-0.1.1.dist-info/METADATA
robotframework_puppeteer_percy-0.1.1.dist-info/WHEEL
robotframework_puppeteer_percy-0.1.1.dist-info/top_level.txt
robotframework_puppeteer_percy-0.1.1.dist-info/RECORD
