Metadata-Version: 2.1
Name: robotframework-puppeteer-percy
Version: 0.1.1
Summary: Puppeteer Percy Library is a puppeteer percy client library for robot framework
Home-page: https://github.com/qahive/robotframework-puppeteer-percy
Author: QA Hive Co.,Ltd
Author-email: support@qahive.com
License: Apache License 2.0
Keywords: robotframework puppeteer percy web-testing automation
Platform: any
Classifier: Programming Language :: Python :: 3
Classifier: Programming Language :: Python :: 3.6
Classifier: Programming Language :: Python :: 3.7
Classifier: License :: OSI Approved :: Apache Software License
Classifier: Operating System :: OS Independent
Classifier: Topic :: Software Development :: Testing
Classifier: Topic :: Software Development :: Testing :: Acceptance
Classifier: Framework :: Robot Framework
Requires-Dist: robotframework (>=3.2.1)
Requires-Dist: pyppeteer (>=0.2.2)
Requires-Dist: requests (>=2)
